django_sockets/__init__.py
django_sockets/broadcaster.py
django_sockets/pubsub.py
django_sockets/sockets.py
django_sockets/utils.py
django_sockets/middleware/__init__.py
django_sockets/middleware/drf.py
django_sockets/middleware/token.py
django_sockets-2.0.0.dist-info/LICENSE
django_sockets-2.0.0.dist-info/METADATA
django_sockets-2.0.0.dist-info/WHEEL
django_sockets-2.0.0.dist-info/top_level.txt
django_sockets-2.0.0.dist-info/RECORD
