Metadata-Version: 2.2
Name: django_sockets
Version: 2.0.0
Summary: Simplified Django websocket processes designed to work with cloud caches
Author-email: Connor Makowski <conmak@mit.edu>
Project-URL: Homepage, https://github.com/connor-makowski/django_sockets
Project-URL: Bug Tracker, https://github.com/connor-makowski/django_sockets/issues
Project-URL: Documentation, https://connor-makowski.github.io/django_sockets/django_sockets.html
Classifier: Programming Language :: Python :: 3
Classifier: License :: OSI Approved :: MIT License
Classifier: Operating System :: OS Independent
Requires-Python: >=3.10
License-File: LICENSE
Requires-Dist: django>=5.0.0
Requires-Dist: asgiref>=3.0.0
Requires-Dist: redis>=5.0.0
Requires-Dist: msgpack>=1.0.0
Requires-Dist: daphne>=4.0.0
Requires-Dist: channels>=4.0.0
